kaminarimon/__init__.py
kaminarimon/auth.py
kaminarimon/backend.py
kaminarimon/views.py
django_kaminarimon-0.2.1.dist-info/licenses/LICENSE
django_kaminarimon-0.2.1.dist-info/WHEEL
django_kaminarimon-0.2.1.dist-info/METADATA
django_kaminarimon-0.2.1.dist-info/RECORD
