Metadata-Version: 2.4
Name: django-kaminarimon
Version: 0.2.1
Summary: Auth(n/z) plugin for Django using kerberos + LDAP
Keywords: django,kerberos,gssapi,spnego,ldap,auth,authentication,authorization,JWT,djangorestframework,DRF
Author: Adrian Torres
Author-email: Adrian Torres <atorresj@redhat.com>
License-Expression: MIT
License-File: LICENSE
Classifier: Development Status :: 4 - Beta
Classifier: License :: OSI Approved :: MIT License
Classifier: Programming Language :: Python :: 3
Classifier: Programming Language :: Python :: 3.9
Classifier: Programming Language :: Python :: 3.10
Classifier: Programming Language :: Python :: 3.11
Classifier: Programming Language :: Python :: 3.12
Classifier: Programming Language :: Python :: 3.13
Classifier: Programming Language :: Python :: 3.14
Classifier: Intended Audience :: Developers
Classifier: Intended Audience :: Information Technology
Classifier: Environment :: Plugins
Classifier: Framework :: Django
Classifier: Natural Language :: English
Classifier: Operating System :: OS Independent
Classifier: Topic :: Software Development :: Libraries
Requires-Dist: django>=4.2.0
Requires-Dist: djangorestframework>=3.15.0
Requires-Dist: djangorestframework-simplejwt>=5.3.1
Requires-Dist: drf-spectacular>=0.27.2
Requires-Dist: kerberos>=1.3.1
Requires-Dist: python-ldap>=3.4.0
Requires-Python: >=3.9
Project-URL: Homepage, https://github.com/RedHatProductSecurity/django-kaminarimon/
Project-URL: Repository, https://github.com/RedHatProductSecurity/django-kaminarimon/
